{
  "coalition-technologies": {
    "company_name": "Coalition Technologies",
    "score": 15,
    "last_seen": "2026-06-28T13:21:03.187902Z"
  },
  "walmart": {
    "company_name": "Walmart",
    "score": 15,
    "last_seen": "2026-06-28T13:21:03.187933Z"
  },
  "ansys": {
    "company_name": "Ansys",
    "score": 15,
    "last_seen": "2026-06-28T13:21:03.187939Z"
  },
  "tiktok": {
    "company_name": "TikTok",
    "score": 15,
    "last_seen": "2026-06-28T13:21:03.187935Z"
  },
  "lemonio": {
    "company_name": "Lemon.io",
    "score": 15,
    "last_seen": "2026-06-28T13:21:03.187892Z"
  },
  "lawnstarter": {
    "company_name": "LawnStarter",
    "score": 15,
    "last_seen": "2026-06-28T13:21:03.187896Z"
  },
  "rentokil-terminix": {
    "company_name": "Rentokil Terminix",
    "score": 15,
    "last_seen": "2026-06-28T13:21:03.187943Z"
  },
  "telus-digital": {
    "company_name": "TELUS Digital",
    "score": 15,
    "last_seen": "2026-06-28T13:21:03.187905Z"
  },
  "ateam": {
    "company_name": "A.Team",
    "score": 15,
    "last_seen": "2026-06-28T13:21:03.187899Z"
  },
  "meta": {
    "company_name": "Meta",
    "score": 15,
    "last_seen": "2026-06-28T13:21:03.187910Z"
  },
  "applied-materials": {
    "company_name": "Applied Materials",
    "score": 15,
    "last_seen": "2026-06-28T13:21:03.187937Z"
  },
  "everai": {
    "company_name": "EverAI",
    "score": 15,
    "last_seen": "2026-06-28T13:21:03.187883Z"
  },
  "work-force-nexus": {
    "company_name": "Work Force Nexus",
    "score": 15,
    "last_seen": "2026-06-27T19:10:22.282409Z"
  },
  "onlinejobsph": {
    "company_name": "OnlineJobs.PH",
    "score": 12,
    "last_seen": "2026-06-28T13:21:03.187948Z"
  },
  "leidos": {
    "company_name": "Leidos",
    "score": 11,
    "last_seen": "2026-06-27T13:15:57.744274Z"
  },
  "perle": {
    "company_name": "Perle",
    "score": 11,
    "last_seen": "2026-06-28T13:21:03.187960Z"
  },
  "travel-planning-professionals": {
    "company_name": "Travel Planning Professionals",
    "score": 10,
    "last_seen": "2026-06-28T13:21:03.187958Z"
  },
  "recruit-lytics-hiring": {
    "company_name": "Recruit Lytics Hiring",
    "score": 10,
    "last_seen": "2026-06-28T13:21:03.187955Z"
  },
  "kindercare-learning-companies": {
    "company_name": "KinderCare Learning Companies",
    "score": 8,
    "last_seen": "2026-06-26T19:35:50.604306Z"
  },
  "strange-face": {
    "company_name": "Strange Face",
    "score": 8,
    "last_seen": "2026-06-27T13:15:57.744294Z"
  },
  "mitre-media": {
    "company_name": "Mitre Media",
    "score": 7,
    "last_seen": "2026-04-28T13:28:55.388235Z"
  },
  "binance": {
    "company_name": "Binance",
    "score": 7,
    "last_seen": "2026-06-28T13:21:03.187919Z"
  },
  "asml": {
    "company_name": "ASML",
    "score": 6,
    "last_seen": "2026-06-28T13:21:03.187941Z"
  },
  "smartsheet": {
    "company_name": "Smartsheet",
    "score": 4,
    "last_seen": "2026-06-27T13:15:57.744254Z"
  },
  "natera": {
    "company_name": "Natera",
    "score": 4,
    "last_seen": "2026-06-27T08:30:01.333625Z"
  },
  "mantech": {
    "company_name": "ManTech",
    "score": 4,
    "last_seen": "2026-06-28T13:21:03.187914Z"
  },
  "aecon-group-inc": {
    "company_name": "Aecon Group Inc.",
    "score": 3,
    "last_seen": "2026-06-26T02:15:57.213016Z"
  },
  "varicent": {
    "company_name": "Varicent",
    "score": 3,
    "last_seen": "2026-06-27T19:10:22.282377Z"
  },
  "doordash": {
    "company_name": "DoorDash",
    "score": 3,
    "last_seen": "2026-06-27T19:10:22.282374Z"
  },
  "upguard": {
    "company_name": "UpGuard",
    "score": 3,
    "last_seen": "2026-06-28T13:21:03.187926Z"
  },
  "m3-usa": {
    "company_name": "M3 USA",
    "score": 3,
    "last_seen": "2026-06-28T13:21:03.187928Z"
  },
  "sanofi": {
    "company_name": "Sanofi",
    "score": 3,
    "last_seen": "2026-06-28T13:21:03.187912Z"
  },
  "innodrei": {
    "company_name": "Innodrei",
    "score": 3,
    "last_seen": "2026-06-28T13:21:03.187946Z"
  },
  "office-of-energy-amp-sustainability": {
    "company_name": "Office of Energy &amp; Sustainability",
    "score": 3,
    "last_seen": "2026-06-28T13:21:03.187950Z"
  },
  "tyviso": {
    "company_name": "Tyviso",
    "score": 3,
    "last_seen": "2026-06-28T13:21:03.187952Z"
  },
  "autodesk": {
    "company_name": "Autodesk",
    "score": 3,
    "last_seen": "2026-06-28T13:21:03.187907Z"
  },
  "ashby": {
    "company_name": "Ashby",
    "score": 2,
    "last_seen": "2026-06-27T13:15:57.744251Z"
  },
  "nachhilfeunterricht": {
    "company_name": "Nachhilfeunterricht",
    "score": 2,
    "last_seen": "2026-06-27T19:10:22.282372Z"
  },
  "remote": {
    "company_name": "Remote",
    "score": 2,
    "last_seen": "2026-06-28T13:21:03.187917Z"
  },
  "elevenlabs": {
    "company_name": "Elevenlabs",
    "score": 2,
    "last_seen": "2026-06-28T13:21:03.187921Z"
  }
}