{
  "coalition-technologies": {
    "company_name": "Coalition Technologies",
    "score": 15,
    "last_seen": "2026-06-11T20:14:28.646931Z"
  },
  "walmart": {
    "company_name": "Walmart",
    "score": 15,
    "last_seen": "2026-06-11T20:14:28.646958Z"
  },
  "ansys": {
    "company_name": "Ansys",
    "score": 15,
    "last_seen": "2026-06-11T20:14:28.646962Z"
  },
  "tiktok": {
    "company_name": "TikTok",
    "score": 15,
    "last_seen": "2026-06-11T20:14:28.646960Z"
  },
  "davita": {
    "company_name": "DaVita",
    "score": 15,
    "last_seen": "2026-06-11T20:14:28.646964Z"
  },
  "kroger": {
    "company_name": "Kroger",
    "score": 15,
    "last_seen": "2026-06-11T20:14:28.646968Z"
  },
  "hitachi-energy": {
    "company_name": "Hitachi Energy",
    "score": 15,
    "last_seen": "2026-06-11T20:14:28.646970Z"
  },
  "everai": {
    "company_name": "EverAI",
    "score": 15,
    "last_seen": "2026-05-26T02:03:30.095479Z"
  },
  "lemonio": {
    "company_name": "Lemon.io",
    "score": 15,
    "last_seen": "2026-06-01T02:38:13.386869Z"
  },
  "leidos": {
    "company_name": "Leidos",
    "score": 15,
    "last_seen": "2026-06-11T20:14:28.646966Z"
  },
  "ateam": {
    "company_name": "A.Team",
    "score": 15,
    "last_seen": "2026-06-11T20:14:28.646938Z"
  },
  "expion-health": {
    "company_name": "Expion Health",
    "score": 15,
    "last_seen": "2026-05-22T02:08:49.540088Z"
  },
  "lawnstarter": {
    "company_name": "LawnStarter",
    "score": 15,
    "last_seen": "2026-06-11T20:14:28.646935Z"
  },
  "rentokil-terminix": {
    "company_name": "Rentokil Terminix",
    "score": 15,
    "last_seen": "2026-06-11T20:14:28.646972Z"
  },
  "telus-digital": {
    "company_name": "TELUS Digital",
    "score": 15,
    "last_seen": "2026-06-11T20:14:28.646921Z"
  },
  "ecs": {
    "company_name": "ECS",
    "score": 13,
    "last_seen": "2026-06-11T15:38:17.994520Z"
  },
  "impact-hr-amp-km-solutions": {
    "company_name": "Impact HR &amp; KM Solutions",
    "score": 11,
    "last_seen": "2026-06-10T14:55:08.509929Z"
  },
  "mitre-media": {
    "company_name": "Mitre Media",
    "score": 11,
    "last_seen": "2026-04-28T13:28:55.388235Z"
  },
  "empresa-confidencial": {
    "company_name": "Empresa Confidencial",
    "score": 9,
    "last_seen": "2026-06-10T20:14:24.385758Z"
  },
  "axiom": {
    "company_name": "Axiom",
    "score": 9,
    "last_seen": "2026-06-11T20:14:28.646940Z"
  },
  "kipp-foundation": {
    "company_name": "KIPP Foundation",
    "score": 8,
    "last_seen": "2026-06-09T19:56:24.985148Z"
  },
  "stem-sync-ai": {
    "company_name": "STEM Sync AI",
    "score": 8,
    "last_seen": "2026-06-11T20:14:28.646994Z"
  },
  "bonkk": {
    "company_name": "Bonkk.",
    "score": 7,
    "last_seen": "2026-06-09T14:19:50.091270Z"
  },
  "mantech": {
    "company_name": "ManTech",
    "score": 7,
    "last_seen": "2026-06-11T20:14:28.646949Z"
  },
  "dana-incorporated": {
    "company_name": "Dana Incorporated",
    "score": 6,
    "last_seen": "2026-06-09T19:56:24.985151Z"
  },
  "celsius": {
    "company_name": "CELSIUS",
    "score": 6,
    "last_seen": "2026-06-05T19:34:30.072682Z"
  },
  "nymbus": {
    "company_name": "Nymbus",
    "score": 5,
    "last_seen": "2026-06-11T20:14:28.646989Z"
  },
  "recruitlytic-hires": {
    "company_name": "RecruitLytic Hires",
    "score": 4,
    "last_seen": "2026-06-09T01:57:43.223945Z"
  },
  "samsara": {
    "company_name": "Samsara",
    "score": 4,
    "last_seen": "2026-06-10T20:14:24.385716Z"
  },
  "motive": {
    "company_name": "Motive",
    "score": 4,
    "last_seen": "2026-06-10T20:14:24.385718Z"
  },
  "instacart": {
    "company_name": "Instacart",
    "score": 4,
    "last_seen": "2026-06-11T15:38:17.994525Z"
  },
  "soracom": {
    "company_name": "SORACOM",
    "score": 4,
    "last_seen": "2026-06-11T20:14:28.646983Z"
  },
  "zscaler": {
    "company_name": "Zscaler",
    "score": 3,
    "last_seen": "2026-06-10T20:14:24.385708Z"
  },
  "remote": {
    "company_name": "Remote",
    "score": 3,
    "last_seen": "2026-06-10T20:14:24.385703Z"
  },
  "think-academy-us": {
    "company_name": "Think Academy US",
    "score": 3,
    "last_seen": "2026-06-11T20:14:28.646943Z"
  },
  "fedex": {
    "company_name": "FedEx",
    "score": 3,
    "last_seen": "2026-06-11T20:14:28.646976Z"
  },
  "curasenseai": {
    "company_name": "CuraSenseAI",
    "score": 3,
    "last_seen": "2026-06-11T20:14:28.646980Z"
  },
  "adani-airport-holdings-ltd": {
    "company_name": "Adani Airport Holdings Ltd",
    "score": 3,
    "last_seen": "2026-06-11T20:14:28.646985Z"
  },
  "intetics": {
    "company_name": "Intetics",
    "score": 3,
    "last_seen": "2026-06-11T20:14:28.646998Z"
  },
  "dreamscape-learn": {
    "company_name": "Dreamscape Learn",
    "score": 2,
    "last_seen": "2026-06-09T19:56:24.985153Z"
  }
}